optext/__init__.py
optext/option.py
optext_python-0.1.1.dist-info/LICENSE
optext_python-0.1.1.dist-info/WHEEL
optext_python-0.1.1.dist-info/METADATA
optext_python-0.1.1.dist-info/RECORD
